LICENSE.txt
MANIFEST.in
README.md
setup.cfg
setup.py
scythe/__init__.py
scythe_game.egg-info/PKG-INFO
scythe_game.egg-info/SOURCES.txt
scythe_game.egg-info/dependency_links.txt
scythe_game.egg-info/not-zip-safe
scythe_game.egg-info/top_level.txt