Metadata-Version: 1.1
Name: scythe-game
Version: 0.1.0
Summary: Modeling the boardgame Scythe
Home-page: https://github.com/chucksmash/scythe.git
Author: Chuck Bassett
Author-email: iamchuckb@gmail.com
License: MIT
Keywords: scythe boardgames
Platform: UNKNOWN
Classifier: Development Status :: 4 - Beta
Classifier: Environment :: Console
Classifier: Intended Audience :: Developers
Classifier: License :: OSI Approved :: MIT License
Classifier: Natural Language :: English
Classifier: Operating System :: OS Independent
Classifier: Programming Language :: Python :: 2
Classifier: Programming Language :: Python :: 2.7
Classifier: Programming Language :: Python :: 3
Classifier: Programming Language :: Python :: 3.3
Classifier: Programming Language :: Python :: 3.4
Classifier: Programming Language :: Python :: 3.5
Classifier: Programming Language :: Python :: 3.6
